rucio/__init__.py
rucio/alembicrevision.py
rucio/vcsversion.py
rucio/version.py
rucio/cli/__init__.py
rucio/cli/account.py
rucio/cli/command.py
rucio/cli/config.py
rucio/cli/did.py
rucio/cli/download.py
rucio/cli/lifetime_exception.py
rucio/cli/opendata.py
rucio/cli/replica.py
rucio/cli/rse.py
rucio/cli/rule.py
rucio/cli/scope.py
rucio/cli/subscription.py
rucio/cli/upload.py
rucio/cli/utils.py
rucio/cli/bin_legacy/__init__.py
rucio/cli/bin_legacy/rucio.py
rucio/cli/bin_legacy/rucio_admin.py
rucio/client/__init__.py
rucio/client/accountclient.py
rucio/client/accountlimitclient.py
rucio/client/baseclient.py
rucio/client/client.py
rucio/client/configclient.py
rucio/client/credentialclient.py
rucio/client/didclient.py
rucio/client/diracclient.py
rucio/client/downloadclient.py
rucio/client/exportclient.py
rucio/client/importclient.py
rucio/client/lifetimeclient.py
rucio/client/lockclient.py
rucio/client/metaconventionsclient.py
rucio/client/opendataclient.py
rucio/client/pingclient.py
rucio/client/replicaclient.py
rucio/client/requestclient.py
rucio/client/richclient.py
rucio/client/rseclient.py
rucio/client/ruleclient.py
rucio/client/scopeclient.py
rucio/client/subscriptionclient.py
rucio/client/touchclient.py
rucio/client/uploadclient.py
rucio/common/__init__.py
rucio/common/bittorrent.py
rucio/common/cache.py
rucio/common/checksum.py
rucio/common/client.py
rucio/common/config.py
rucio/common/constants.py
rucio/common/constraints.py
rucio/common/didtype.py
rucio/common/exception.py
rucio/common/extra.py
rucio/common/logging.py
rucio/common/pcache.py
rucio/common/plugins.py
rucio/common/policy.py
rucio/common/stomp_utils.py
rucio/common/stopwatch.py
rucio/common/test_rucio_server.py
rucio/common/types.py
rucio/common/utils.py
rucio/common/dumper/__init__.py
rucio/common/dumper/consistency.py
rucio/common/dumper/data_models.py
rucio/common/dumper/path_parsing.py
rucio/common/schema/__init__.py
rucio/common/schema/generic.py
rucio/common/schema/generic_multi_vo.py
rucio_clients-39.1.0.dist-info/licenses/LICENSE
rucio_clients-39.1.0.dist-info/METADATA
rucio_clients-39.1.0.dist-info/WHEEL
rucio_clients-39.1.0.dist-info/top_level.txt
rucio_clients-39.1.0.dist-info/RECORD
