Metadata-Version: 2.4
Name: rucio-clients
Version: 39.1.0
Summary: Rucio client package
Author-email: Rucio <rucio-contact@cern.ch>
Maintainer-email: Rucio <rucio-contact@cern.ch>
License-Expression: Apache-2.0
Project-URL: Homepage, https://rucio.cern.ch/
Project-URL: Documentation, https://rucio.cern.ch/documentation/
Project-URL: Repository, https://github.com/rucio/rucio.git
Project-URL: Bug Tracker, https://github.com/rucio/rucio/issues
Project-URL: Changelog, https://rucio.cern.ch/documentation/release-notes/
Classifier: Development Status :: 5 - Production/Stable
Classifier: Intended Audience :: Information Technology
Classifier: Intended Audience :: System Administrators
Classifier: Operating System :: POSIX :: Linux
Classifier: Natural Language :: English
Classifier: Programming Language :: Python
Classifier: Programming Language :: Python :: 3
Classifier: Programming Language :: Python :: 3.9
Classifier: Programming Language :: Python :: 3.10
Requires-Python: >=3.9
License-File: LICENSE
Requires-Dist: click
Requires-Dist: requests
Requires-Dist: urllib3
Requires-Dist: dogpile-cache
Requires-Dist: packaging
Requires-Dist: tabulate
Requires-Dist: jsonschema
Requires-Dist: rich
Requires-Dist: typing_extensions
Provides-Extra: ssh
Requires-Dist: paramiko; extra == "ssh"
Provides-Extra: kerberos
Requires-Dist: kerberos; extra == "kerberos"
Requires-Dist: pykerberos; extra == "kerberos"
Requires-Dist: requests-kerberos; extra == "kerberos"
Provides-Extra: swift
Requires-Dist: python-swiftclient; extra == "swift"
Provides-Extra: argcomplete
Requires-Dist: argcomplete; extra == "argcomplete"
Provides-Extra: sftp
Requires-Dist: paramiko; extra == "sftp"
Provides-Extra: dumper
Requires-Dist: python-magic; extra == "dumper"
Dynamic: license-file
